[
null,
{"id":1,"animationId":0,"consumable":false,"damage":{"critical":false,"elementId":0,"formula":"0","type":0,"variance":20},"description":"ごく普通のナイフだ","effects":[],"hitType":0,"iconIndex":0,"itypeId":1,"name":"ナイフ","note":"","occasion":2,"price":50,"repeats":1,"scope":0,"speed":0,"successRate":100,"tpGain":0},
{"id":2,"animationId":0,"consumable":false,"damage":{"critical":false,"elementId":0,"formula":"0","type":0,"variance":20},"description":"まだ死んで間もないようだ","effects":[],"hitType":0,"iconIndex":0,"itypeId":1,"name":"ネズミの死体","note":"","occasion":2,"price":100,"repeats":1,"scope":0,"speed":0,"successRate":100,"tpGain":0},
{"id":3,"animationId":0,"consumable":false,"damage":{"critical":false,"elementId":0,"formula":"0","type":0,"variance":20},"description":"ごく普通のリンゴだ","effects":[],"hitType":0,"iconIndex":0,"itypeId":1,"name":"リンゴ","note":"","occasion":2,"price":200,"repeats":1,"scope":0,"speed":0,"successRate":100,"tpGain":0},
{"id":4,"animationId":0,"consumable":false,"damage":{"critical":false,"elementId":0,"formula":"b.mhp / 2","type":0,"variance":20},"description":"ごく普通のつるはしだ\n何かを壊すのに使えそう","effects":[],"hitType":0,"iconIndex":0,"itypeId":1,"name":"つるはし","note":"","occasion":2,"price":300,"repeats":1,"scope":0,"speed":0,"successRate":100,"tpGain":0},
{"id":5,"animationId":0,"consumable":false,"damage":{"critical":false,"elementId":0,"formula":"0","type":0,"variance":20},"description":"途中で見つけたメモだ","effects":[{"code":44,"dataId":1,"value1":1,"value2":0}],"hitType":0,"iconIndex":0,"itypeId":1,"name":"メモ","note":"","occasion":0,"price":0,"repeats":1,"scope":0,"speed":0,"successRate":100,"tpGain":0},
{"id":6,"animationId":0,"consumable":false,"damage":{"critical":false,"elementId":0,"formula":"0","type":0,"variance":20},"description":"自分が持っていた包丁だ","effects":[{"code":44,"dataId":2,"value1":1,"value2":0}],"hitType":0,"iconIndex":0,"itypeId":1,"name":"自分の包丁","note":"","occasion":2,"price":0,"repeats":1,"scope":0,"speed":0,"successRate":100,"tpGain":0}
]